nhncloud_sms/__init__.py
nhncloud_sms/sms.py
tests/__init__.py
tests/tests_helper.py
tests/helpers/__init__.py
tests/helpers/my_helper.py
tests/unit/__init__.py
tests/unit/test_sms.py
nhncloud_sms-0.1.7.dist-info/LICENSE
nhncloud_sms-0.1.7.dist-info/METADATA
nhncloud_sms-0.1.7.dist-info/WHEEL
nhncloud_sms-0.1.7.dist-info/top_level.txt
nhncloud_sms-0.1.7.dist-info/RECORD
