Metadata-Version: 2.1
Name: nhncloud-sms
Version: 0.1.7
Summary: A Python library to send SMS using NHN Cloud API
Home-page: https://github.com/RUNNERS-IM/python-nhncloud-sms
Author: RUNNERS
Author-email: dev@runners.im
License: UNKNOWN
Platform: UNKNOWN
Classifier: Environment :: Web Environment
Classifier: Intended Audience :: Developers
Classifier: License :: OSI Approved :: MIT License
Classifier: Operating System :: OS Independent
Classifier: Programming Language :: Python
Classifier: Programming Language :: Python :: 3
Classifier: Topic :: Software Development :: Libraries :: Python Modules
Requires-Dist: requests
